akamaiproperty/__init__.py
akamaiproperty/akamaiproperty.py
akamaiproperty/http_calls.py
akamaiproperty-2.7.dist-info/LICENSE
akamaiproperty-2.7.dist-info/METADATA
akamaiproperty-2.7.dist-info/WHEEL
akamaiproperty-2.7.dist-info/top_level.txt
akamaiproperty-2.7.dist-info/RECORD
