Metadata-Version: 2.1
Name: akamaiproperty
Version: 2.7
Summary: A Pip Package for Akamai Property
Home-page: https://github.com/Achuthananda/AkamaiPropertyManager
Author: Achuthananda M P
Author-email: achuthadivine@gmail.com
Keywords: Akamai Property CDN AkamaiConfigs Edge
Classifier: Programming Language :: Python :: 3
Classifier: License :: OSI Approved :: MIT License
Classifier: Operating System :: OS Independent
License-File: LICENSE
Requires-Dist: edgegrid-python
Requires-Dist: requests
